pocket_recommendations.py
pocket_recommendations-0.1.1.dist-info/LICENSE
pocket_recommendations-0.1.1.dist-info/WHEEL
pocket_recommendations-0.1.1.dist-info/METADATA
pocket_recommendations-0.1.1.dist-info/RECORD
