Metadata-Version: 2.1
Name: pocket-recommendations
Version: 0.1.1
Summary: Unofficial library to get a feed of one's Pocket recommendations
Home-page: https://github.com/honzajavorek/pocket-recommendations
License: MIT
Author: Honza Javorek
Author-email: mail@honzajavorek.cz
Requires-Python: >=3.6,<4.0
Classifier: License :: OSI Approved :: MIT License
Classifier: Programming Language :: Python :: 3
Classifier: Programming Language :: Python :: 3.6
Classifier: Programming Language :: Python :: 3.7
Classifier: Programming Language :: Python :: 3.8
Requires-Dist: cssselect (>=1.1.0,<2.0.0)
Requires-Dist: lxml (>=4.5.1,<5.0.0)
Project-URL: Documentation, https://github.com/honzajavorek/pocket-recommendations#readme
Project-URL: Repository, https://github.com/honzajavorek/pocket-recommendations
